[{"timestamp":"2024-12-09T01:44:34.756Z","count":0,"uniques":0},{"timestamp":"2024-12-10T01:43:01.050Z","count":0,"uniques":0},{"timestamp":"2024-12-11T01:41:47.144Z","count":0,"uniques":0},{"timestamp":"2024-12-12T01:41:17.204Z","count":0,"uniques":0},{"timestamp":"2024-12-13T01:42:31.894Z","count":0,"uniques":0},{"timestamp":"2024-12-14T01:38:06.380Z","count":0,"uniques":0},{"timestamp":"2024-12-15T01:47:16.710Z","count":0,"uniques":0},{"timestamp":"2024-12-16T01:44:38.578Z","count":0,"uniques":0}]
