[{"timestamp":"2025-04-10T01:41:26.498Z","count":0,"uniques":0},{"timestamp":"2025-04-11T01:41:58.287Z","count":0,"uniques":0},{"timestamp":"2025-04-12T01:39:23.995Z","count":0,"uniques":0},{"timestamp":"2025-04-13T03:07:59.207Z","count":0,"uniques":0},{"timestamp":"2025-04-14T01:45:24.674Z","count":0,"uniques":0},{"timestamp":"2025-04-15T01:44:37.241Z","count":0,"uniques":0},{"timestamp":"2025-04-16T01:44:07.815Z","count":0,"uniques":0},{"timestamp":"2025-04-17T01:42:32.825Z","count":0,"uniques":0}]
