[{"timestamp":"2024-10-22T01:26:50.469Z","count":0,"uniques":0},{"timestamp":"2024-10-23T01:25:30.912Z","count":0,"uniques":0},{"timestamp":"2024-10-24T01:25:38.510Z","count":0,"uniques":0},{"timestamp":"2024-10-25T01:26:31.194Z","count":0,"uniques":0},{"timestamp":"2024-10-26T01:23:42.704Z","count":0,"uniques":0},{"timestamp":"2024-10-27T01:39:06.452Z","count":0,"uniques":0},{"timestamp":"2024-10-28T01:37:18.608Z","count":0,"uniques":0},{"timestamp":"2024-10-29T01:27:38.320Z","count":0,"uniques":0}]
