[{"timestamp":"2025-01-05T01:39:40.553Z","count":0,"uniques":0},{"timestamp":"2025-01-06T01:37:42.941Z","count":0,"uniques":0},{"timestamp":"2025-01-07T01:26:47.850Z","count":0,"uniques":0},{"timestamp":"2025-01-08T01:26:21.668Z","count":0,"uniques":0},{"timestamp":"2025-01-09T01:25:49.039Z","count":0,"uniques":0},{"timestamp":"2025-01-10T01:36:11.477Z","count":0,"uniques":0},{"timestamp":"2025-01-11T01:26:44.432Z","count":0,"uniques":0},{"timestamp":"2025-01-12T01:41:05.731Z","count":0,"uniques":0}]
