[{"timestamp":"2024-11-17T01:42:15.890Z","count":0,"uniques":0},{"timestamp":"2024-11-18T01:40:22.218Z","count":0,"uniques":0},{"timestamp":"2024-11-19T01:38:21.850Z","count":0,"uniques":0},{"timestamp":"2024-11-20T01:39:20.354Z","count":0,"uniques":0},{"timestamp":"2024-11-21T01:37:20.930Z","count":0,"uniques":0},{"timestamp":"2024-11-22T01:38:24.688Z","count":0,"uniques":0},{"timestamp":"2024-11-23T01:27:21.808Z","count":0,"uniques":0},{"timestamp":"2024-11-24T01:42:45.894Z","count":0,"uniques":0}]
