[{"timestamp":"2023-12-23T01:05:35.160Z","count":0,"uniques":0},{"timestamp":"2023-12-24T01:12:15.618Z","count":0,"uniques":0},{"timestamp":"2023-12-25T01:09:27.177Z","count":0,"uniques":0},{"timestamp":"2023-12-26T01:06:31.789Z","count":0,"uniques":0},{"timestamp":"2023-12-27T01:06:32.647Z","count":0,"uniques":0},{"timestamp":"2023-12-28T00:00:00.000Z","count":1,"uniques":1},{"timestamp":"2023-12-29T00:58:07.575Z","count":0,"uniques":0},{"timestamp":"2023-12-30T01:06:03.861Z","count":0,"uniques":0}]
