[{"timestamp":"2026-01-20T05:48:50.053Z","count":0,"uniques":0},{"timestamp":"2026-01-21T05:48:50.053Z","count":0,"uniques":0},{"timestamp":"2026-01-22T05:48:50.053Z","count":0,"uniques":0},{"timestamp":"2026-01-23T05:48:50.053Z","count":0,"uniques":0},{"timestamp":"2026-01-24T05:48:50.053Z","count":0,"uniques":0},{"timestamp":"2026-01-25T05:48:50.053Z","count":0,"uniques":0},{"timestamp":"2026-01-26T05:48:50.053Z","count":0,"uniques":0},{"timestamp":"2026-01-27T05:48:50.053Z","count":0,"uniques":0},{"timestamp":"2026-01-28T05:48:50.053Z","count":0,"uniques":0},{"timestamp":"2026-01-29T05:48:50.053Z","count":0,"uniques":0},{"timestamp":"2026-01-30T05:48:50.053Z","count":0,"uniques":0},{"timestamp":"2026-01-31T05:48:50.053Z","count":0,"uniques":0},{"timestamp":"2026-02-01T05:48:50.053Z","count":0,"uniques":0},{"timestamp":"2026-02-02T05:48:50.053Z","count":0,"uniques":0},{"timestamp":"2026-02-03T05:48:50.053Z","count":0,"uniques":0},{"timestamp":"2026-02-04T05:48:50.053Z","count":0,"uniques":0},{"timestamp":"2026-02-05T02:24:12.434Z","count":0,"uniques":0},{"timestamp":"2026-02-06T02:24:09.615Z","count":0,"uniques":0},{"timestamp":"2026-02-07T02:13:01.481Z","count":0,"uniques":0},{"timestamp":"2026-02-08T02:46:38.217Z","count":0,"uniques":0},{"timestamp":"2026-02-09T02:32:02.059Z","count":0,"uniques":0},{"timestamp":"2026-02-10T02:40:10.983Z","count":0,"uniques":0},{"timestamp":"2026-02-11T02:37:39.437Z","count":0,"uniques":0},{"timestamp":"2026-02-12T02:32:03.052Z","count":0,"uniques":0},{"timestamp":"2026-02-13T02:33:37.290Z","count":0,"uniques":0},{"timestamp":"2026-02-14T02:21:42.912Z","count":0,"uniques":0},{"timestamp":"2026-02-15T02:33:51.834Z","count":0,"uniques":0},{"timestamp":"2026-02-16T02:29:56.557Z","count":0,"uniques":0},{"timestamp":"2026-02-17T02:26:31.201Z","count":0,"uniques":0},{"timestamp":"2026-02-18T02:29:52.221Z","count":0,"uniques":0},{"timestamp":"2026-02-19T02:28:58.475Z","count":0,"uniques":0}]
