[{"timestamp":"2024-12-30T01:35:15.041Z","count":0,"uniques":0},{"timestamp":"2024-12-31T01:24:46.511Z","count":0,"uniques":0},{"timestamp":"2025-01-01T01:39:46.751Z","count":0,"uniques":0},{"timestamp":"2025-01-02T01:24:33.014Z","count":0,"uniques":0},{"timestamp":"2025-01-03T01:25:32.854Z","count":0,"uniques":0},{"timestamp":"2025-01-04T01:23:51.476Z","count":0,"uniques":0},{"timestamp":"2025-01-05T01:38:52.439Z","count":0,"uniques":0},{"timestamp":"2025-01-06T01:36:52.842Z","count":0,"uniques":0}]
