[{"timestamp":"2025-07-23T01:59:33.789Z","count":0,"uniques":0},{"timestamp":"2025-07-24T01:58:32.332Z","count":0,"uniques":0},{"timestamp":"2025-07-25T01:58:22.227Z","count":0,"uniques":0},{"timestamp":"2025-07-26T01:55:02.657Z","count":0,"uniques":0},{"timestamp":"2025-07-27T02:07:59.183Z","count":0,"uniques":0},{"timestamp":"2025-07-28T02:05:33.919Z","count":0,"uniques":0},{"timestamp":"2025-07-29T02:11:00.172Z","count":0,"uniques":0},{"timestamp":"2025-07-30T00:00:00.000Z","count":8,"uniques":1},{"timestamp":"2025-07-31T02:01:04.682Z","count":0,"uniques":0},{"timestamp":"2025-08-01T02:11:17.798Z","count":0,"uniques":0},{"timestamp":"2025-08-02T00:00:00.000Z","count":2,"uniques":1},{"timestamp":"2025-08-03T02:09:33.670Z","count":0,"uniques":0},{"timestamp":"2025-08-04T02:09:36.496Z","count":0,"uniques":0},{"timestamp":"2025-08-05T02:04:23.085Z","count":0,"uniques":0},{"timestamp":"2025-08-06T02:02:21.582Z","count":0,"uniques":0},{"timestamp":"2025-08-07T02:02:50.618Z","count":0,"uniques":0},{"timestamp":"2025-08-08T02:02:14.212Z","count":0,"uniques":0},{"timestamp":"2025-08-09T01:51:27.944Z","count":0,"uniques":0},{"timestamp":"2025-08-10T02:06:05.111Z","count":0,"uniques":0},{"timestamp":"2025-08-11T02:02:29.354Z","count":0,"uniques":0},{"timestamp":"2025-08-12T00:00:00.000Z","count":1,"uniques":1},{"timestamp":"2025-08-13T00:00:00.000Z","count":2,"uniques":1},{"timestamp":"2025-08-14T01:53:13.861Z","count":0,"uniques":0},{"timestamp":"2025-08-15T01:53:38.900Z","count":0,"uniques":0},{"timestamp":"2025-08-16T01:48:15.256Z","count":0,"uniques":0},{"timestamp":"2025-08-17T01:59:07.533Z","count":0,"uniques":0},{"timestamp":"2025-08-18T01:59:49.926Z","count":0,"uniques":0},{"timestamp":"2025-08-19T01:47:07.417Z","count":0,"uniques":0},{"timestamp":"2025-08-20T01:45:38.742Z","count":0,"uniques":0},{"timestamp":"2025-08-21T01:44:33.087Z","count":0,"uniques":0},{"timestamp":"2025-08-22T01:44:59.344Z","count":0,"uniques":0}]
