[{"timestamp":"2024-06-19T01:13:47.537Z","count":0,"uniques":0},{"timestamp":"2024-06-20T01:11:48.053Z","count":0,"uniques":0},{"timestamp":"2024-06-21T00:00:00.000Z","count":32,"uniques":1},{"timestamp":"2024-06-22T01:12:00.684Z","count":0,"uniques":0},{"timestamp":"2024-06-23T00:00:00.000Z","count":1,"uniques":1},{"timestamp":"2024-06-24T00:00:00.000Z","count":1,"uniques":1},{"timestamp":"2024-06-25T00:00:00.000Z","count":14,"uniques":2},{"timestamp":"2024-06-26T01:13:32.464Z","count":0,"uniques":0}]
