[{"timestamp":"2024-12-23T01:27:28.022Z","count":0,"uniques":0},{"timestamp":"2024-12-24T01:25:50.773Z","count":0,"uniques":0},{"timestamp":"2024-12-25T01:24:49.282Z","count":0,"uniques":0},{"timestamp":"2024-12-26T01:25:10.825Z","count":0,"uniques":0},{"timestamp":"2024-12-27T01:25:29.316Z","count":0,"uniques":0},{"timestamp":"2024-12-28T01:24:08.284Z","count":0,"uniques":0},{"timestamp":"2024-12-29T00:00:00.000Z","count":2,"uniques":2},{"timestamp":"2024-12-30T01:35:46.062Z","count":0,"uniques":0},{"timestamp":"2024-12-31T01:25:17.388Z","count":0,"uniques":0},{"timestamp":"2025-01-01T01:40:19.880Z","count":0,"uniques":0},{"timestamp":"2025-01-02T01:25:04.530Z","count":0,"uniques":0},{"timestamp":"2025-01-03T01:26:04.343Z","count":0,"uniques":0},{"timestamp":"2025-01-04T01:24:22.995Z","count":0,"uniques":0},{"timestamp":"2025-01-05T01:39:30.189Z","count":0,"uniques":0},{"timestamp":"2025-01-06T01:37:31.989Z","count":0,"uniques":0},{"timestamp":"2025-01-07T01:26:38.196Z","count":0,"uniques":0},{"timestamp":"2025-01-08T01:26:12.274Z","count":0,"uniques":0},{"timestamp":"2025-01-09T01:25:39.679Z","count":0,"uniques":0},{"timestamp":"2025-01-10T01:36:02.318Z","count":0,"uniques":0},{"timestamp":"2025-01-11T01:26:34.901Z","count":0,"uniques":0},{"timestamp":"2025-01-12T01:40:56.456Z","count":0,"uniques":0},{"timestamp":"2025-01-13T01:38:01.599Z","count":0,"uniques":0},{"timestamp":"2025-01-14T01:22:31.268Z","count":0,"uniques":0},{"timestamp":"2025-01-15T00:00:00.000Z","count":20,"uniques":1},{"timestamp":"2025-01-16T01:23:38.577Z","count":0,"uniques":0},{"timestamp":"2025-01-17T01:23:12.183Z","count":0,"uniques":0},{"timestamp":"2025-01-18T01:21:23.726Z","count":0,"uniques":0},{"timestamp":"2025-01-19T01:36:17.293Z","count":0,"uniques":0},{"timestamp":"2025-01-20T01:24:50.626Z","count":0,"uniques":0},{"timestamp":"2025-01-21T01:23:27.641Z","count":0,"uniques":0},{"timestamp":"2025-01-22T01:25:35.279Z","count":0,"uniques":0}]
