[{"timestamp":"2024-12-19T01:38:49.873Z","count":0,"uniques":0},{"timestamp":"2024-12-20T01:26:33.044Z","count":0,"uniques":0},{"timestamp":"2024-12-21T01:24:33.027Z","count":0,"uniques":0},{"timestamp":"2024-12-22T01:39:18.505Z","count":0,"uniques":0},{"timestamp":"2024-12-23T01:27:28.022Z","count":0,"uniques":0},{"timestamp":"2024-12-24T01:25:50.773Z","count":0,"uniques":0},{"timestamp":"2024-12-25T01:24:49.282Z","count":0,"uniques":0},{"timestamp":"2024-12-26T01:25:10.825Z","count":0,"uniques":0}]
