[{"timestamp":"2025-08-03T02:09:19.305Z","count":0,"uniques":0},{"timestamp":"2025-08-04T02:09:22.882Z","count":0,"uniques":0},{"timestamp":"2025-08-05T02:04:08.559Z","count":0,"uniques":0},{"timestamp":"2025-08-06T02:02:07.469Z","count":0,"uniques":0},{"timestamp":"2025-08-07T02:02:36.708Z","count":0,"uniques":0},{"timestamp":"2025-08-08T02:01:59.811Z","count":0,"uniques":0},{"timestamp":"2025-08-09T01:51:13.840Z","count":0,"uniques":0},{"timestamp":"2025-08-10T02:05:50.661Z","count":0,"uniques":0}]
