[{"timestamp":"2025-10-04T01:26:41.761Z","count":0,"uniques":0},{"timestamp":"2025-10-05T01:46:50.626Z","count":0,"uniques":0},{"timestamp":"2025-10-06T01:40:26.263Z","count":0,"uniques":0},{"timestamp":"2025-10-07T01:38:08.851Z","count":0,"uniques":0},{"timestamp":"2025-10-08T00:00:00.000Z","count":1,"uniques":1},{"timestamp":"2025-10-09T01:39:15.503Z","count":0,"uniques":0},{"timestamp":"2025-10-10T01:39:54.128Z","count":0,"uniques":0},{"timestamp":"2025-10-11T01:35:28.386Z","count":0,"uniques":0}]
