[{"timestamp":"2024-12-17T01:40:50.246Z","count":0,"uniques":0},{"timestamp":"2024-12-18T06:27:55.964Z","count":0,"uniques":0},{"timestamp":"2024-12-19T01:38:25.285Z","count":0,"uniques":0},{"timestamp":"2024-12-20T01:26:06.438Z","count":0,"uniques":0},{"timestamp":"2024-12-21T01:24:10.311Z","count":0,"uniques":0},{"timestamp":"2024-12-22T01:38:55.170Z","count":0,"uniques":0},{"timestamp":"2024-12-23T01:27:02.171Z","count":0,"uniques":0},{"timestamp":"2024-12-24T00:00:00.000Z","count":1,"uniques":1}]
