[{"timestamp":"2025-11-21T01:46:02.619Z","count":0,"uniques":0},{"timestamp":"2025-11-22T01:42:20.753Z","count":0,"uniques":0},{"timestamp":"2025-11-23T01:59:58.703Z","count":0,"uniques":0},{"timestamp":"2025-11-24T01:54:07.156Z","count":0,"uniques":0},{"timestamp":"2025-11-25T01:48:03.159Z","count":0,"uniques":0},{"timestamp":"2025-11-26T01:47:47.235Z","count":0,"uniques":0},{"timestamp":"2025-11-27T01:45:51.449Z","count":0,"uniques":0},{"timestamp":"2025-11-28T01:45:43.690Z","count":0,"uniques":0}]
