[{"timestamp":"2024-09-03T00:00:00.000Z","count":2,"uniques":1},{"timestamp":"2024-09-04T00:00:00.000Z","count":1,"uniques":1},{"timestamp":"2024-09-05T00:00:00.000Z","count":1,"uniques":1},{"timestamp":"2024-09-06T01:20:34.360Z","count":0,"uniques":0},{"timestamp":"2024-09-07T01:19:08.778Z","count":0,"uniques":0},{"timestamp":"2024-09-08T01:26:38.252Z","count":0,"uniques":0},{"timestamp":"2024-09-09T01:22:54.117Z","count":0,"uniques":0},{"timestamp":"2024-09-10T01:21:38.725Z","count":0,"uniques":0}]
